[
  {
    "Name": "Beef",
    "Description": "A prime cut of beef.",
    "Type": 10,
    "Damage": 0,
    "Defense": 0,
    "Weight": 2,
    "Value": 200,
    "CurrentDurability": 0,
    "MaximumDurability": 0,
    "Strength": 0,
    "Vitality": 0,
    "Dexterity": 0,
    "Wisdom": 0,
    "RestoreHealth": 40,
    "RestoreMagic": 0,
    "Cures": false,
    "MinimumLevel": 0,
    "CanSell": true,
    "IsSold": true,
    "AllowedClassesJson": ""
  },
  {
    "Name": "Bread",
    "Description": "A slice of bread.",
    "Type": 10,
    "Damage": 0,
    "Defense": 0,
    "Weight": 0,
    "Value": 50,
    "CurrentDurability": 0,
    "MaximumDurability": 0,
    "Strength": 0,
    "Vitality": 0,
    "Dexterity": 0,
    "Wisdom": 0,
    "RestoreHealth": 10,
    "RestoreMagic": 0,
    "Cures": false,
    "MinimumLevel": 0,
    "CanSell": true,
    "IsSold": true,
    "AllowedClassesJson": ""
  },
  {
    "Name": "Chicken",
    "Description": "A piece of grilled chicken.",
    "Type": 10,
    "Damage": 0,
    "Defense": 0,
    "Weight": 2,
    "Value": 150,
    "CurrentDurability": 0,
    "MaximumDurability": 0,
    "Strength": 0,
    "Vitality": 0,
    "Dexterity": 0,
    "Wisdom": 0,
    "RestoreHealth": 30,
    "RestoreMagic": 0,
    "Cures": false,
    "MinimumLevel": 0,
    "CanSell": true,
    "IsSold": true,
    "AllowedClassesJson": ""
  },
  {
    "Name": "Cracker",
    "Description": "A cracker.",
    "Type": 10,
    "Damage": 0,
    "Defense": 0,
    "Weight": 0,
    "Value": 25,
    "CurrentDurability": 0,
    "MaximumDurability": 0,
    "Strength": 0,
    "Vitality": 0,
    "Dexterity": 0,
    "Wisdom": 0,
    "RestoreHealth": 5,
    "RestoreMagic": 0,
    "Cures": false,
    "MinimumLevel": 0,
    "CanSell": true,
    "IsSold": true,
    "AllowedClassesJson": ""
  },
  {
    "Name": "Soup",
    "Description": "A small container of soup.",
    "Type": 10,
    "Damage": 0,
    "Defense": 0,
    "Weight": 2,
    "Value": 75,
    "CurrentDurability": 0,
    "MaximumDurability": 0,
    "Strength": 0,
    "Vitality": 0,
    "Dexterity": 0,
    "Wisdom": 0,
    "RestoreHealth": 15,
    "RestoreMagic": 0,
    "Cures": false,
    "MinimumLevel": 0,
    "CanSell": true,
    "IsSold": true,
    "AllowedClassesJson": ""
  }
]
